{
  "Amount": 100000,
  "CustemerId": "6a799ef1-aa7e-486b-875e-f7602e4ce426",
  "Customer": null,
  "PackageId": "33333333-3333-3333-3333-333333333333",
  "Package": null,
  "DueDate": "2025-12-24T16:29:58.8322138Z",
  "Note": null,
  "Status": 0,
  "LastModified": "2025-11-24T16:29:58.8314351Z",
  "BlockchainHash": null,
  "BlockchainTxHash": "PENDING",
  "BlockchainRecordedAt": null,
  "IsTampered": false,
  "TamperedDetectedAt": null,
  "IsReported": false,
  "ReportedAt": null,
  "CreatedBy": null,
  "CreatedAt": "2025-11-24T16:29:58.8325003Z",
  "UpdatedBy": null,
  "UpdatedAt": "2025-11-24T16:29:58.8326595Z",
  "isDeleted": false,
  "Id": "88f08cc7-cda6-4ab5-bb6e-f51e37f0a63b"
}